word2lex/__init__.py
word2lex/word2lex.py
word2lex/data/__init__.py
word2lex/data/britain.json
word2lex/data/canada.json
word2lex/data/news_media.json
word2lex/data/politics_en.json
word2lex/data/twitter.json
word2lex/data/usa.json
word2lex/utils/__init__.py
word2lex/utils/custom_vader.py
word2lex-0.0.1.dist-info/LICENSE
word2lex-0.0.1.dist-info/METADATA
word2lex-0.0.1.dist-info/WHEEL
word2lex-0.0.1.dist-info/top_level.txt
word2lex-0.0.1.dist-info/RECORD
