Metadata-Version: 2.1
Name: word2lex
Version: 0.0.1
Summary: Sentiment dictionary induction for political texts using word embeddings
Home-page: https://github.com/lrheault/word2lex
Author: L. Rheault
License: MIT license
Keywords: word2lex
Platform: UNKNOWN
Classifier: Development Status :: 2 - Pre-Alpha
Classifier: Intended Audience :: Developers
Classifier: License :: OSI Approved :: MIT License
Classifier: Natural Language :: English
Classifier: Programming Language :: Python :: 3
Classifier: Programming Language :: Python :: 3.5
Classifier: Programming Language :: Python :: 3.6
Classifier: Programming Language :: Python :: 3.7
Classifier: Programming Language :: Python :: 3.8
Requires-Python: >=3.5
